{"id": "R000588", "update_date": "2018-12-23", "biography_text": "RICHMOND, Cedric, a Representative from Louisiana; born in New Orleans, Orleans Parish, La., September 13, 1973; graduated from Benjamin Franklin High School, New Orleans, La., 1991; B.A., Morehouse College, Atlanta, Ga., 1995; J.D., Tulane University, New Orleans, La., 1998; member of the Louisiana state house of representatives, 1999-2011; unsuccessful candidate for nomination to the One Hundred Eleventh Congress in 2008; elected as a Democrat to the One Hundred Twelfth and to the three succeeding Congresses (January 3, 2011-present).", "name": {"last": "Richmond", "first": "Cedric"}, "date_of_birth": {"month": 9, "day": 13, "year": 1973}, "place_of_birth": "New Orleans, Orleans Parish, La.", "post_secondary_degrees": [{"degree": "B.A.", "year": 1995, "institution": "Morehouse College, Atlanta, Ga."}, {"degree": "J.D.", "year": 1998, "institution": "Tulane University, New Orleans, La."}]}